datamol/__init__.py
datamol/_sanifix4.py
datamol/_version.py
datamol/align.py
datamol/cluster.py
datamol/convert.py
datamol/fp.py
datamol/graph.py
datamol/io.py
datamol/log.py
datamol/mcs.py
datamol/mol.py
datamol/molar.py
datamol/similarity.py
datamol/types.py
datamol/conformers/__init__.py
datamol/conformers/_conformers.py
datamol/conformers/_features.py
datamol/data/__init__.py
datamol/data/cdk2.sdf
datamol/data/chembl_approved_drugs.parquet
datamol/data/chembl_drugs.csv
datamol/data/chembl_samples.csv
datamol/data/freesolv.csv
datamol/data/reactions.json
datamol/data/salts_solvents.smi
datamol/data/solubility.test.sdf
datamol/data/solubility.train.sdf
datamol/descriptors/__init__.py
datamol/descriptors/compute.py
datamol/descriptors/descriptors.py
datamol/fragment/__init__.py
datamol/fragment/_assemble.py
datamol/fragment/_fragment.py
datamol/isomers/__init__.py
datamol/isomers/_enumerate.py
datamol/isomers/_structural.py
datamol/predictors/__init__.py
datamol/predictors/esol.py
datamol/reactions/__init__.py
datamol/reactions/_attachments.py
datamol/reactions/_reactions.py
datamol/scaffold/__init__.py
datamol/scaffold/_fuzzy.py
datamol/utils/__init__.py
datamol/utils/decorators.py
datamol/utils/fs.py
datamol/utils/jobs.py
datamol/utils/perf.py
datamol/utils/testing.py
datamol/viz/__init__.py
datamol/viz/_circle_grid.py
datamol/viz/_conformers.py
datamol/viz/_lasso_highlight.py
datamol/viz/_substructure.py
datamol/viz/_viz.py
datamol/viz/utils.py
datamol-0.12.5.dist-info/LICENSE
datamol-0.12.5.dist-info/METADATA
datamol-0.12.5.dist-info/WHEEL
datamol-0.12.5.dist-info/top_level.txt
datamol-0.12.5.dist-info/RECORD
