Metadata-Version: 2.1
Name: datamol
Version: 0.12.5
Summary: A python library to work with molecules. Built on top of RDKit.
Author-email: Hadrien Mary <hadrien@valencediscovery.com>
License: Apache
Project-URL: Website, https://datamol.io
Project-URL: Source Code, https://github.com/datamol-io/datamol
Project-URL: Bug Tracker, https://github.com/datamol-io/datamol/issues
Project-URL: Documentation, https://docs.datamol.io
Classifier: Development Status :: 5 - Production/Stable
Classifier: Intended Audience :: Developers
Classifier: Intended Audience :: Healthcare Industry
Classifier: Intended Audience :: Science/Research
Classifier: Topic :: Scientific/Engineering :: Artificial Intelligence
Classifier: Topic :: Scientific/Engineering :: Bio-Informatics
Classifier: Topic :: Scientific/Engineering :: Information Analysis
Classifier: Topic :: Scientific/Engineering :: Medical Science Apps.
Classifier: Natural Language :: English
Classifier: Operating System :: OS Independent
Classifier: Programming Language :: Python
Classifier: Programming Language :: Python :: 3
Classifier: Programming Language :: Python :: 3.8
Classifier: Programming Language :: Python :: 3.9
Classifier: Programming Language :: Python :: 3.10
Classifier: Programming Language :: Python :: 3.11
Requires-Python: >=3.8
License-File: LICENSE
Requires-Dist: tqdm
Requires-Dist: loguru
Requires-Dist: joblib
Requires-Dist: fsspec >=2021.9
Requires-Dist: pandas
Requires-Dist: numpy
Requires-Dist: scipy
Requires-Dist: matplotlib
Requires-Dist: pillow
Requires-Dist: selfies
Requires-Dist: platformdirs
Requires-Dist: scikit-learn
Requires-Dist: packaging
Requires-Dist: typing-extensions
Requires-Dist: importlib-resources
Requires-Dist: rdkit
